spidertool_yyds/__init__.py
spidertool_yyds/spidertool_yyds.py
spidertool_yyds-0.8.0.dist-info/LICENSE
spidertool_yyds-0.8.0.dist-info/METADATA
spidertool_yyds-0.8.0.dist-info/WHEEL
spidertool_yyds-0.8.0.dist-info/top_level.txt
spidertool_yyds-0.8.0.dist-info/RECORD
