Metadata-Version: 2.1
Name: spidertool-yyds
Version: 0.8.0
Summary: My short description for my project.
Home-page: https://blog.csdn.net/qq_39295540
Author: Casey
Author-email: 395280963@qq.com
License: MIT
Platform: UNKNOWN
Classifier: License :: OSI Approved :: MIT License
Classifier: Programming Language :: Python
Classifier: Programming Language :: Python :: 3
Classifier: Programming Language :: Python :: 3.6
Classifier: Programming Language :: Python :: Implementation :: CPython
Classifier: Programming Language :: Python :: Implementation :: PyPy
Requires-Python: >=3.6.0
License-File: LICENSE
Requires-Dist: pymysql
Requires-Dist: DBUtils
